chess_analyzer/__init__.py
chess_analyzer/server.py
chess_game_review-0.1.0.dist-info/licenses/LICENSE
chess_game_review-0.1.0.dist-info/METADATA
chess_game_review-0.1.0.dist-info/WHEEL
chess_game_review-0.1.0.dist-info/entry_points.txt
chess_game_review-0.1.0.dist-info/top_level.txt
chess_game_review-0.1.0.dist-info/RECORD
