Metadata-Version: 2.4
Name: chess-game-review
Version: 0.1.0
Summary: A Flask server for chess game analysis and game review using Stockfish.
Home-page: https://github.com/bhatganeshdarshan/chess-game-review
Author: Ganeshdarshan Bhat
Author-email: bhatganeshdarshan10@gmail.com
Classifier: Programming Language :: Python :: 3
Classifier: License :: OSI Approved :: MIT License
Classifier: Operating System :: OS Independent
Classifier: Framework :: Flask
Classifier: Topic :: Games/Entertainment :: Board Games
Classifier: Topic :: Software Development :: Libraries :: Python Modules
Requires-Python: >=3.7
License-File: LICENSE
Requires-Dist: Flask>=2.0
Requires-Dist: python-chess>=1.9
Requires-Dist: Flask-CORS>=3.0
Dynamic: author
Dynamic: author-email
Dynamic: classifier
Dynamic: description
Dynamic: description-content-type
Dynamic: home-page
Dynamic: license-file
Dynamic: requires-dist
Dynamic: requires-python
Dynamic: summary
